CHANGES.txt
COPYRIGHT.txt
LICENSE.txt
README.txt
setup.cfg
setup.py
repoze/__init__.py
repoze.bfg.jinja2.egg-info/PKG-INFO
repoze.bfg.jinja2.egg-info/SOURCES.txt
repoze.bfg.jinja2.egg-info/dependency_links.txt
repoze.bfg.jinja2.egg-info/entry_points.txt
repoze.bfg.jinja2.egg-info/namespace_packages.txt
repoze.bfg.jinja2.egg-info/not-zip-safe
repoze.bfg.jinja2.egg-info/requires.txt
repoze.bfg.jinja2.egg-info/top_level.txt
repoze/bfg/__init__.py
repoze/bfg/jinja2/__init__.py
repoze/bfg/jinja2/bindings.py
repoze/bfg/jinja2/configure.zcml
repoze/bfg/jinja2/paster.py
repoze/bfg/jinja2/paster_template/+project+.ini_tmpl
repoze/bfg/jinja2/paster_template/CHANGES.txt_tmpl
repoze/bfg/jinja2/paster_template/README.txt_tmpl
repoze/bfg/jinja2/paster_template/ez_setup.py
repoze/bfg/jinja2/paster_template/setup.py_tmpl
repoze/bfg/jinja2/paster_template/+package+/__init__.py
repoze/bfg/jinja2/paster_template/+package+/configure.zcml
repoze/bfg/jinja2/paster_template/+package+/models.py
repoze/bfg/jinja2/paster_template/+package+/run.py_tmpl
repoze/bfg/jinja2/paster_template/+package+/tests.py_tmpl
repoze/bfg/jinja2/paster_template/+package+/views.py_tmpl
repoze/bfg/jinja2/paster_template/+package+/templates/mytemplate.jinja2
repoze/bfg/jinja2/paster_template/+package+/templates/static/default.css
repoze/bfg/jinja2/paster_template/+package+/templates/static/templatelicense.txt
repoze/bfg/jinja2/paster_template/+package+/templates/static/images/img01.gif
repoze/bfg/jinja2/paster_template/+package+/templates/static/images/img02.gif
repoze/bfg/jinja2/paster_template/+package+/templates/static/images/img03.gif
repoze/bfg/jinja2/paster_template/+package+/templates/static/images/img04.gif
repoze/bfg/jinja2/paster_template/+package+/templates/static/images/spacer.gif
repoze/bfg/jinja2/tests/__init__.py
repoze/bfg/jinja2/tests/test_bindings.py
repoze/bfg/jinja2/tests/templates/extends.jinja2
repoze/bfg/jinja2/tests/templates/helloworld.jinja2