Metadata-Version: 1.0
Name: repoze.bfg.jinja2
Version: 0.6
Summary: Jinja2 template bindings for repoze.bfg
Home-page: http://www.repoze.org
Author: Agendaless Consulting
Author-email: repoze-dev@lists.repoze.org
License: BSD-derived (http://www.repoze.org/LICENSE.txt)
Keywords: web wsgi zope
Platform: UNKNOWN
Classifier: Intended Audience :: Developers
Classifier: Programming Language :: Python
Classifier: Framework :: BFG
Classifier: License :: Repoze Public License
